confer.py
confer-0.0.2.dist-info/METADATA
confer-0.0.2.dist-info/WHEEL
confer-0.0.2.dist-info/entry_points.txt
confer-0.0.2.dist-info/top_level.txt
confer-0.0.2.dist-info/RECORD
